scicheck/_message.py
scicheck/errors/__init__.py
scicheck/errors/base.py
scicheck/errors/numeric.py
scicheck/errors/path.py
scicheck/errors/string.py
scicheck/numeric.py
scicheck/path.py
scicheck/type.py
scicheck/utils.py
scicheck-0.1.dist-info/LICENSE
scicheck-0.1.dist-info/METADATA
scicheck-0.1.dist-info/WHEEL
scicheck-0.1.dist-info/RECORD
