Metadata-Version: 2.3
Name: scicheck
Version: 0.1
Summary: Input validation for scientific codes
License: MIT
Keywords: validation
Author: Jonathan King
Author-email: jking@usgs.gov
Maintainer: Jonathan King
Maintainer-email: jking@usgs.gov
Requires-Python: >=3.10
Classifier: License :: OSI Approved :: MIT License
Classifier: Programming Language :: Python :: 3
Classifier: Programming Language :: Python :: 3.10
Classifier: Programming Language :: Python :: 3.11
Classifier: Programming Language :: Python :: 3.12
Classifier: Programming Language :: Python :: 3.13
